LICENSE
MANIFEST.in
README.md
setup.cfg
setup.py
versioneer.py
veros_bgc/__init__.py
veros_bgc/_version.py
veros_bgc/settings.py
veros_bgc/variables.py
veros_bgc.egg-info/PKG-INFO
veros_bgc.egg-info/SOURCES.txt
veros_bgc.egg-info/dependency_links.txt
veros_bgc.egg-info/entry_points.txt
veros_bgc.egg-info/not-zip-safe
veros_bgc.egg-info/requires.txt
veros_bgc.egg-info/top_level.txt
veros_bgc/core/__init__.py
veros_bgc/core/atmospherefluxes.py
veros_bgc/core/npzd.py
veros_bgc/core/npzd_rules.py
veros_bgc/core/npzd_tracers.py
veros_bgc/diagnostics/__init__.py
veros_bgc/diagnostics/npzd_monitor.py
veros_bgc/setup/__init__.py
veros_bgc/setup/bgc_global_4deg/__init__.py
veros_bgc/setup/bgc_global_4deg/assets.yml
veros_bgc/setup/bgc_global_4deg/bgc_global_four_degree.py
veros_bgc/setup/bgc_global_4deg/npzd.yml