Metadata-Version: 2.1
Name: veros-bgc
Version: 0.1.3
Summary: Biogeochemistry plugin for Veros, the versatile ocean simulator.
Home-page: https://veros-bgc.readthedocs.io
Author: Dion Häfner (NBI Copenhagen)
Author-email: dion.haefner@nbi.ku.dk
License: MIT
Keywords: oceanography python parallel numpy multi-core geophysics ocean-model bohrium mpi4py biogeochemistry
Platform: UNKNOWN
Classifier: Development Status :: 3 - Alpha
Classifier: Intended Audience :: Science/Research
Classifier: License :: OSI Approved :: MIT License
Classifier: Programming Language :: Python :: 3
Classifier: Programming Language :: Python :: 3.5
Classifier: Programming Language :: Python :: 3.6
Classifier: Programming Language :: Python :: 3.7
Classifier: Programming Language :: Python :: Implementation :: CPython
Classifier: Topic :: Scientific/Engineering
Classifier: Operating System :: Microsoft :: Windows
Classifier: Operating System :: POSIX
Classifier: Operating System :: Unix
Classifier: Operating System :: MacOS
Requires-Python: >3.5.2
License-File: LICENSE
